delocate/__init__.py
delocate/_version.py
delocate/delocating.py
delocate/fuse.py
delocate/libsana.py
delocate/pkginfo.py
delocate/py.typed
delocate/tmpdirs.py
delocate/tools.py
delocate/wheeltools.py
delocate/cmd/__init__.py
delocate/cmd/common.py
delocate/cmd/delocate_addplat.py
delocate/cmd/delocate_fuse.py
delocate/cmd/delocate_listdeps.py
delocate/cmd/delocate_merge.py
delocate/cmd/delocate_patch.py
delocate/cmd/delocate_path.py
delocate/cmd/delocate_wheel.py
delocate/tests/__init__.py
delocate/tests/conftest.py
delocate/tests/env_tools.py
delocate/tests/pytest_tools.py
delocate/tests/test_delocating.py
delocate/tests/test_fuse.py
delocate/tests/test_install_names.py
delocate/tests/test_libsana.py
delocate/tests/test_scripts.py
delocate/tests/test_tmpdirs.py
delocate/tests/test_tools.py
delocate/tests/test_wheelies.py
delocate/tests/test_wheeltools.py
delocate/tests/data/.gitignore
delocate/tests/data/a.o
delocate/tests/data/binary_example.bin
delocate/tests/data/empty
delocate/tests/data/fakepkg1-1.0-cp37-abi3-macosx_10_9_universal2.whl
delocate/tests/data/fakepkg2-1.0-py3-none-any.whl
delocate/tests/data/fakepkg2.bad_patch
delocate/tests/data/fakepkg2.patch
delocate/tests/data/fakepkg_namespace-1.0-cp37-abi3-macosx_10_9_universal2.whl
delocate/tests/data/fakepkg_rpath-1.0-cp37-abi3-macosx_10_9_universal2.whl
delocate/tests/data/fakepkg_toplevel-1.0-cp37-abi3-macosx_10_9_universal2.whl
delocate/tests/data/icon.ico
delocate/tests/data/liba.a
delocate/tests/data/liba.dylib
delocate/tests/data/liba_12.dylib
delocate/tests/data/liba_12_1.dylib
delocate/tests/data/liba_both.dylib
delocate/tests/data/libam1-arch.dylib
delocate/tests/data/libam1.dylib
delocate/tests/data/libam1_12.dylib
delocate/tests/data/libb.dylib
delocate/tests/data/libc.dylib
delocate/tests/data/libc_12.dylib
delocate/tests/data/libextfunc.dylib
delocate/tests/data/libextfunc2_rpath.dylib
delocate/tests/data/libextfunc_rpath.dylib
delocate/tests/data/make_libs.sh
delocate-0.13.0.dist-info/AUTHORS
delocate-0.13.0.dist-info/LICENSE
delocate-0.13.0.dist-info/METADATA
delocate-0.13.0.dist-info/WHEEL
delocate-0.13.0.dist-info/entry_points.txt
delocate-0.13.0.dist-info/top_level.txt
delocate-0.13.0.dist-info/RECORD
