Metadata-Version: 2.2
Name: delocate
Version: 0.13.0
Summary: Move macOS dynamic libraries into package
Author-email: Matthew Brett <matthew.brett@gmail.com>
Maintainer-email: Matthew Brett <matthew.brett@gmail.com>, Kyle Benesch <4b796c65+github@gmail.com>
License: Copyright (c) 2014-2025, Matthew Brett and the Delocate contributors.
Project-URL: Homepage, http://github.com/matthew-brett/delocate
Classifier: Development Status :: 5 - Production/Stable
Classifier: Environment :: Console
Classifier: Intended Audience :: Developers
Classifier: License :: OSI Approved :: BSD License
Classifier: Natural Language :: English
Classifier: Operating System :: MacOS :: MacOS X
Classifier: Programming Language :: Python :: 3
Classifier: Topic :: Software Development :: Libraries :: Python Modules
Classifier: Topic :: Software Development :: Build Tools
Classifier: Typing :: Typed
Requires-Python: >=3.9
License-File: LICENSE
License-File: AUTHORS
Requires-Dist: packaging>=20.9
Requires-Dist: typing_extensions>=4.12.2
Requires-Dist: macholib
